<?xml version='1.0' encoding='UTF-8' standalone='yes'?>
<sea-summary time="Sep 13, 2012 3:56:37 PM"
 project="TestBoundedCollections">

  <count LockModel="1"/>

  <count ProposedPromiseDrop="8"/>

  <count ThreadSafePromiseDrop="2"/>

  <count ResultFolderDrop="10"/>

  <count ResultDrop="17"/>

  <count AnnotationBoundsPromiseDrop="1"/>

  <promise-drop type="AnnotationBoundsPromiseDrop"
   offset="322"
   length="48"
   line="16"
   path="TestBoundedCollections/src/test/Test.java"
   uri="file:/Users/aarong/git/regression/regression/TestBoundedCollections/src/test/Test.java"
   file="file:/Users/aarong/git/regression/regression/TestBoundedCollections/src/test/Test.java"
   hash="375185648"
   context="-877171204"
   id="3367"
   message="AnnotationBounds(containable = {&quot;C&quot;}) on X"
   category="Annotation bounds"
   to-be-checked-by-analysis="true"
   from-src="true"
   message-id="(136,containable = {&quot;C&quot;},X)"
   checked-by-analysis="true"
   derived-from-src="true"
   full-type="edu.cmu.cs.fluid.sea.drops.promises.AnnotationBoundsPromiseDrop"/>

  <result-folder-drop type="ResultFolderDrop"
   offset="298"
   length="20"
   line="13"
   path="TestBoundedCollections/src/test/Test.java"
   uri="file:/Users/aarong/git/regression/regression/TestBoundedCollections/src/test/Test.java"
   file="file:/Users/aarong/git/regression/regression/TestBoundedCollections/src/test/Test.java"
   hash="-205428493"
   context="-1226327922"
   message-id="(495,X&lt;Object&gt;)"
   message="Parameterized type X&lt;Object&gt;"
   id="3368"
   derived-from-src="true"
   full-type="edu.cmu.cs.fluid.sea.ResultFolderDrop"/>

  <result-folder-drop type="ResultFolderDrop"
   offset="647"
   length="68"
   line="24"
   path="TestBoundedCollections/src/test/Example.java"
   uri="file:/Users/aarong/git/regression/regression/TestBoundedCollections/src/test/Example.java"
   file="file:/Users/aarong/git/regression/regression/TestBoundedCollections/src/test/Example.java"
   hash="-956272932"
   context="1400164821"
   id="3370"
   message="Parameterized type ConcurrentMap&lt;Location,Player&gt;"
   message-id="(495,ConcurrentMap&lt;Location,Player&gt;)"
   derived-from-src="true"
   proved-consistent="true"
   full-type="edu.cmu.cs.fluid.sea.ResultFolderDrop"/>

  <result-folder-drop type="ResultFolderDrop"
   offset="351"
   length="34"
   line="15"
   path="TestBoundedCollections/src/test/Example.java"
   uri="file:/Users/aarong/git/regression/regression/TestBoundedCollections/src/test/Example.java"
   file="file:/Users/aarong/git/regression/regression/TestBoundedCollections/src/test/Example.java"
   hash="704134106"
   context="-941332293"
   id="3372"
   message="Parameterized type CopyOnWriteArrayList&lt;String&gt;"
   message-id="(495,CopyOnWriteArrayList&lt;String&gt;)"
   derived-from-src="true"
   proved-consistent="true"
   full-type="edu.cmu.cs.fluid.sea.ResultFolderDrop"/>

  <result-folder-drop type="ResultFolderDrop"
   offset="413"
   length="56"
   line="16"
   path="TestBoundedCollections/src/test/Example.java"
   uri="file:/Users/aarong/git/regression/regression/TestBoundedCollections/src/test/Example.java"
   file="file:/Users/aarong/git/regression/regression/TestBoundedCollections/src/test/Example.java"
   hash="-1471867003"
   context="-941332293"
   id="3373"
   message="Parameterized type CopyOnWriteArrayList&lt;CopyOnWriteArrayList&lt;String&gt;&gt;"
   message-id="(495,CopyOnWriteArrayList&lt;CopyOnWriteArrayList&lt;String&gt;&gt;)"
   derived-from-src="true"
   proved-consistent="true"
   full-type="edu.cmu.cs.fluid.sea.ResultFolderDrop"/>

  <result-folder-drop type="ResultFolderDrop"
   offset="438"
   length="28"
   line="16"
   path="TestBoundedCollections/src/test/Example.java"
   uri="file:/Users/aarong/git/regression/regression/TestBoundedCollections/src/test/Example.java"
   file="file:/Users/aarong/git/regression/regression/TestBoundedCollections/src/test/Example.java"
   hash="704134106"
   context="-941332293"
   id="3374"
   message="Parameterized type CopyOnWriteArrayList&lt;String&gt;"
   message-id="(495,CopyOnWriteArrayList&lt;String&gt;)"
   derived-from-src="true"
   proved-consistent="true"
   full-type="edu.cmu.cs.fluid.sea.ResultFolderDrop"/>

  <result-folder-drop type="ResultFolderDrop"
   offset="261"
   length="34"
   line="12"
   path="TestBoundedCollections/src/test/Test.java"
   uri="file:/Users/aarong/git/regression/regression/TestBoundedCollections/src/test/Test.java"
   file="file:/Users/aarong/git/regression/regression/TestBoundedCollections/src/test/Test.java"
   hash="-1119661981"
   context="-1226327922"
   id="3376"
   message="Parameterized type Vector&lt;Vector&lt;String&gt;&gt;"
   message-id="(495,Vector&lt;Vector&lt;String&gt;&gt;)"
   derived-from-src="true"
   proved-consistent="true"
   full-type="edu.cmu.cs.fluid.sea.ResultFolderDrop"/>

  <result-folder-drop type="ResultFolderDrop"
   offset="276"
   length="14"
   line="12"
   path="TestBoundedCollections/src/test/Test.java"
   uri="file:/Users/aarong/git/regression/regression/TestBoundedCollections/src/test/Test.java"
   file="file:/Users/aarong/git/regression/regression/TestBoundedCollections/src/test/Test.java"
   hash="-344500742"
   context="-1226327922"
   id="3377"
   message="Parameterized type Vector&lt;String&gt;"
   message-id="(495,Vector&lt;String&gt;)"
   derived-from-src="true"
   proved-consistent="true"
   full-type="edu.cmu.cs.fluid.sea.ResultFolderDrop"/>

  <result-folder-drop type="ResultFolderDrop"
   offset="194"
   length="31"
   line="10"
   path="TestBoundedCollections/src/test/Test.java"
   uri="file:/Users/aarong/git/regression/regression/TestBoundedCollections/src/test/Test.java"
   file="file:/Users/aarong/git/regression/regression/TestBoundedCollections/src/test/Test.java"
   hash="1461306422"
   context="-543256980"
   message-id="(495,Hashtable&lt;String,Object&gt;)"
   message="Parameterized type Hashtable&lt;String,Object&gt;"
   id="3379"
   derived-from-src="true"
   full-type="edu.cmu.cs.fluid.sea.ResultFolderDrop"/>

  <result-folder-drop type="ResultFolderDrop"
   offset="155"
   length="71"
   line="10"
   path="TestBoundedCollections/src/test/Test.java"
   uri="file:/Users/aarong/git/regression/regression/TestBoundedCollections/src/test/Test.java"
   file="file:/Users/aarong/git/regression/regression/TestBoundedCollections/src/test/Test.java"
   hash="1461306422"
   context="-1226327922"
   message-id="(495,Hashtable&lt;String,Object&gt;)"
   message="Parameterized type Hashtable&lt;String,Object&gt;"
   id="3380"
   derived-from-src="true"
   full-type="edu.cmu.cs.fluid.sea.ResultFolderDrop"/>

  <result-folder-drop type="ResultFolderDrop"
   offset="229"
   length="29"
   line="11"
   path="TestBoundedCollections/src/test/Test.java"
   uri="file:/Users/aarong/git/regression/regression/TestBoundedCollections/src/test/Test.java"
   file="file:/Users/aarong/git/regression/regression/TestBoundedCollections/src/test/Test.java"
   hash="787417592"
   context="-1226327922"
   id="3382"
   message="Parameterized type Stack&lt;Integer&gt;"
   message-id="(495,Stack&lt;Integer&gt;)"
   derived-from-src="true"
   proved-consistent="true"
   full-type="edu.cmu.cs.fluid.sea.ResultFolderDrop"/>

  <promise-drop type="LockModel"
   offset="2147483647"
   line="0"
   path="java.lang/Object.class"
   file="java.lang/Object.class"
   hash="1709211273"
   context="1063877011"
   id="3684"
   message="RegionLock java.lang.Object.MUTEX is this protects WaitQueue on Object"
   category="Concurrency"
   to-be-checked-by-analysis="true"
   uses-red-dot="true"
   from-src="true"
   message-id="(100,java.lang.Object.MUTEX,this,WaitQueue,Object)"
   derived-from-src="true"
   proved-consistent="true"
   full-type="edu.cmu.cs.fluid.sea.drops.promises.LockModel"/>

  <promise-drop type="ThreadSafePromiseDrop"
   offset="758"
   length="27"
   line="30"
   path="TestBoundedCollections/src/test/Example.java"
   uri="file:/Users/aarong/git/regression/regression/TestBoundedCollections/src/test/Example.java"
   file="file:/Users/aarong/git/regression/regression/TestBoundedCollections/src/test/Example.java"
   hash="612235867"
   context="-1788674083"
   id="3722"
   message="ThreadSafe on Player"
   category="Concurrency"
   to-be-checked-by-analysis="true"
   from-src="true"
   message-id="(112,Player)"
   checked-by-analysis="true"
   derived-from-src="true"
   proved-consistent="true"
   full-type="edu.cmu.cs.fluid.sea.drops.promises.ThreadSafePromiseDrop"/>

  <result-drop type="ResultDrop"
   offset="758"
   length="27"
   line="30"
   path="TestBoundedCollections/src/test/Example.java"
   uri="file:/Users/aarong/git/regression/regression/TestBoundedCollections/src/test/Example.java"
   file="file:/Users/aarong/git/regression/regression/TestBoundedCollections/src/test/Example.java"
   hash="1063877011"
   context="-470108362"
   id="3723"
   message="Supertype java.lang.Object is thread safe"
   from-src="true"
   message-id="(414,java.lang.Object)"
   derived-from-src="true"
   consistent="true"
   proved-consistent="true"
   full-type="edu.cmu.cs.fluid.sea.ResultDrop"/>

  <result-drop type="ResultDrop"
   offset="758"
   length="27"
   line="30"
   path="TestBoundedCollections/src/test/Example.java"
   uri="file:/Users/aarong/git/regression/regression/TestBoundedCollections/src/test/Example.java"
   file="file:/Users/aarong/git/regression/regression/TestBoundedCollections/src/test/Example.java"
   hash="-216263291"
   context="-1788674083"
   id="3724"
   message="Trivially thread safe: class has no state"
   from-src="true"
   message-id="(408)"
   derived-from-src="true"
   consistent="true"
   proved-consistent="true"
   full-type="edu.cmu.cs.fluid.sea.ResultDrop"/>

  <promise-drop type="ThreadSafePromiseDrop"
   offset="727"
   length="29"
   line="27"
   path="TestBoundedCollections/src/test/Example.java"
   uri="file:/Users/aarong/git/regression/regression/TestBoundedCollections/src/test/Example.java"
   file="file:/Users/aarong/git/regression/regression/TestBoundedCollections/src/test/Example.java"
   hash="-1014744333"
   context="-907102799"
   id="3725"
   message="ThreadSafe on Location"
   category="Concurrency"
   to-be-checked-by-analysis="true"
   from-src="true"
   message-id="(112,Location)"
   checked-by-analysis="true"
   derived-from-src="true"
   proved-consistent="true"
   full-type="edu.cmu.cs.fluid.sea.drops.promises.ThreadSafePromiseDrop"/>

  <result-drop type="ResultDrop"
   offset="727"
   length="29"
   line="27"
   path="TestBoundedCollections/src/test/Example.java"
   uri="file:/Users/aarong/git/regression/regression/TestBoundedCollections/src/test/Example.java"
   file="file:/Users/aarong/git/regression/regression/TestBoundedCollections/src/test/Example.java"
   hash="1063877011"
   context="-780797238"
   id="3726"
   message="Supertype java.lang.Object is thread safe"
   from-src="true"
   message-id="(414,java.lang.Object)"
   derived-from-src="true"
   consistent="true"
   proved-consistent="true"
   full-type="edu.cmu.cs.fluid.sea.ResultDrop"/>

  <result-drop type="ResultDrop"
   offset="727"
   length="29"
   line="27"
   path="TestBoundedCollections/src/test/Example.java"
   uri="file:/Users/aarong/git/regression/regression/TestBoundedCollections/src/test/Example.java"
   file="file:/Users/aarong/git/regression/regression/TestBoundedCollections/src/test/Example.java"
   hash="-1624112935"
   context="-907102799"
   id="3727"
   message="Trivially thread safe: class has no state"
   from-src="true"
   message-id="(408)"
   derived-from-src="true"
   consistent="true"
   proved-consistent="true"
   full-type="edu.cmu.cs.fluid.sea.ResultDrop"/>

  <ir-drop type="ProposedPromiseDrop"
   offset="219"
   line="11"
   path="TestBoundedCollections/src/test/Example.java"
   uri="file:/Users/aarong/git/regression/regression/TestBoundedCollections/src/test/Example.java"
   file="file:/Users/aarong/git/regression/regression/TestBoundedCollections/src/test/Example.java"
   hash="1512540055"
   context="-552300085"
   id="5014"
   message="ProposedPromiseDrop @RegionEffects(none)"
   target-project="TestBoundedCollections"
   java-annotation="@RegionEffects(&quot;none&quot;)"
   annotation-type="RegionEffects"
   contents="none"
   origin="CODE"
   from-project="TestBoundedCollections"
   full-type="edu.cmu.cs.fluid.sea.ProposedPromiseDrop"/>

  <ir-drop type="ProposedPromiseDrop"
   offset="155"
   line="10"
   path="TestBoundedCollections/src/test/Test.java"
   uri="file:/Users/aarong/git/regression/regression/TestBoundedCollections/src/test/Test.java"
   file="file:/Users/aarong/git/regression/regression/TestBoundedCollections/src/test/Test.java"
   hash="-771460111"
   context="-1797576045"
   id="5015"
   message="ProposedPromiseDrop @RegionEffects(none)"
   target-project="TestBoundedCollections"
   java-annotation="@RegionEffects(&quot;none&quot;)"
   annotation-type="RegionEffects"
   contents="none"
   origin="CODE"
   from-project="TestBoundedCollections"
   full-type="edu.cmu.cs.fluid.sea.ProposedPromiseDrop"/>

  <ir-drop type="ProposedPromiseDrop"
   offset="322"
   line="16"
   path="TestBoundedCollections/src/test/Test.java"
   uri="file:/Users/aarong/git/regression/regression/TestBoundedCollections/src/test/Test.java"
   file="file:/Users/aarong/git/regression/regression/TestBoundedCollections/src/test/Test.java"
   hash="1941155557"
   context="640567399"
   id="5016"
   message="ProposedPromiseDrop @RegionEffects(none)"
   target-project="TestBoundedCollections"
   java-annotation="@RegionEffects(&quot;none&quot;)"
   annotation-type="RegionEffects"
   contents="none"
   origin="CODE"
   from-project="TestBoundedCollections"
   full-type="edu.cmu.cs.fluid.sea.ProposedPromiseDrop"/>

  <ir-drop type="ProposedPromiseDrop"
   offset="304"
   length="178"
   line="14"
   path="TestBoundedCollections/src/test/Example.java"
   uri="file:/Users/aarong/git/regression/regression/TestBoundedCollections/src/test/Example.java"
   file="file:/Users/aarong/git/regression/regression/TestBoundedCollections/src/test/Example.java"
   hash="-375038328"
   context="-941332293"
   id="5017"
   message="ProposedPromiseDrop @RegionEffects(writes this:Instance)"
   target-project="TestBoundedCollections"
   java-annotation="@RegionEffects(&quot;writes this:Instance&quot;)"
   annotation-type="RegionEffects"
   contents="writes this:Instance"
   origin="CODE"
   from-project="TestBoundedCollections"
   full-type="edu.cmu.cs.fluid.sea.ProposedPromiseDrop"/>

  <ir-drop type="ProposedPromiseDrop"
   offset="488"
   length="153"
   line="19"
   path="TestBoundedCollections/src/test/Example.java"
   uri="file:/Users/aarong/git/regression/regression/TestBoundedCollections/src/test/Example.java"
   file="file:/Users/aarong/git/regression/regression/TestBoundedCollections/src/test/Example.java"
   hash="773421692"
   context="-297059207"
   id="5018"
   message="ProposedPromiseDrop @RegionEffects(writes this:Instance)"
   target-project="TestBoundedCollections"
   java-annotation="@RegionEffects(&quot;writes this:Instance&quot;)"
   annotation-type="RegionEffects"
   contents="writes this:Instance"
   origin="CODE"
   from-project="TestBoundedCollections"
   full-type="edu.cmu.cs.fluid.sea.ProposedPromiseDrop"/>

  <ir-drop type="ProposedPromiseDrop"
   offset="647"
   length="68"
   line="24"
   path="TestBoundedCollections/src/test/Example.java"
   uri="file:/Users/aarong/git/regression/regression/TestBoundedCollections/src/test/Example.java"
   file="file:/Users/aarong/git/regression/regression/TestBoundedCollections/src/test/Example.java"
   hash="1216382326"
   context="1400164821"
   id="5019"
   message="ProposedPromiseDrop @RegionEffects(none)"
   target-project="TestBoundedCollections"
   java-annotation="@RegionEffects(&quot;none&quot;)"
   annotation-type="RegionEffects"
   contents="none"
   origin="CODE"
   from-project="TestBoundedCollections"
   full-type="edu.cmu.cs.fluid.sea.ProposedPromiseDrop"/>

  <ir-drop type="ProposedPromiseDrop"
   offset="727"
   line="27"
   path="TestBoundedCollections/src/test/Example.java"
   uri="file:/Users/aarong/git/regression/regression/TestBoundedCollections/src/test/Example.java"
   file="file:/Users/aarong/git/regression/regression/TestBoundedCollections/src/test/Example.java"
   hash="549643796"
   context="-723384333"
   id="5020"
   message="ProposedPromiseDrop @RegionEffects(none)"
   target-project="TestBoundedCollections"
   java-annotation="@RegionEffects(&quot;none&quot;)"
   annotation-type="RegionEffects"
   contents="none"
   origin="CODE"
   from-project="TestBoundedCollections"
   full-type="edu.cmu.cs.fluid.sea.ProposedPromiseDrop"/>

  <ir-drop type="ProposedPromiseDrop"
   offset="758"
   line="30"
   path="TestBoundedCollections/src/test/Example.java"
   uri="file:/Users/aarong/git/regression/regression/TestBoundedCollections/src/test/Example.java"
   file="file:/Users/aarong/git/regression/regression/TestBoundedCollections/src/test/Example.java"
   hash="319774080"
   context="2082228915"
   id="5021"
   message="ProposedPromiseDrop @RegionEffects(none)"
   target-project="TestBoundedCollections"
   java-annotation="@RegionEffects(&quot;none&quot;)"
   annotation-type="RegionEffects"
   contents="none"
   origin="CODE"
   from-project="TestBoundedCollections"
   full-type="edu.cmu.cs.fluid.sea.ProposedPromiseDrop"/>

  <result-drop type="ResultDrop"
   offset="351"
   length="34"
   line="15"
   path="TestBoundedCollections/src/test/Example.java"
   uri="file:/Users/aarong/git/regression/regression/TestBoundedCollections/src/test/Example.java"
   file="file:/Users/aarong/git/regression/regression/TestBoundedCollections/src/test/Example.java"
   hash="704134106"
   context="-941332293"
   id="5022"
   message="Type String satisfies the annotation bound ReferenceObject || ThreadSafe on type formal E"
   enclosed-in-folder="true"
   from-src="true"
   message-id="(496,String,ReferenceObject || ThreadSafe,E)"
   derived-from-src="true"
   consistent="true"
   proved-consistent="true"
   full-type="edu.cmu.cs.fluid.sea.ResultDrop"/>

  <result-drop type="ResultDrop"
   offset="155"
   length="71"
   line="10"
   path="TestBoundedCollections/src/test/Test.java"
   uri="file:/Users/aarong/git/regression/regression/TestBoundedCollections/src/test/Test.java"
   file="file:/Users/aarong/git/regression/regression/TestBoundedCollections/src/test/Test.java"
   hash="1461306422"
   context="-1226327922"
   id="5023"
   message="Type Object does not satisfy the annotation bound ReferenceObject || ThreadSafe on type formal V"
   enclosed-in-folder="true"
   from-src="true"
   message-id="(497,Object,ReferenceObject || ThreadSafe,V)"
   derived-from-src="true"
   full-type="edu.cmu.cs.fluid.sea.ResultDrop"/>

  <result-drop type="ResultDrop"
   offset="155"
   length="71"
   line="10"
   path="TestBoundedCollections/src/test/Test.java"
   uri="file:/Users/aarong/git/regression/regression/TestBoundedCollections/src/test/Test.java"
   file="file:/Users/aarong/git/regression/regression/TestBoundedCollections/src/test/Test.java"
   hash="1461306422"
   context="-1226327922"
   id="5024"
   message="Type String satisfies the annotation bound ReferenceObject || ThreadSafe on type formal K"
   enclosed-in-folder="true"
   from-src="true"
   message-id="(496,String,ReferenceObject || ThreadSafe,K)"
   derived-from-src="true"
   consistent="true"
   proved-consistent="true"
   full-type="edu.cmu.cs.fluid.sea.ResultDrop"/>

  <result-drop type="ResultDrop"
   offset="413"
   length="56"
   line="16"
   path="TestBoundedCollections/src/test/Example.java"
   uri="file:/Users/aarong/git/regression/regression/TestBoundedCollections/src/test/Example.java"
   file="file:/Users/aarong/git/regression/regression/TestBoundedCollections/src/test/Example.java"
   hash="-1471867003"
   context="-941332293"
   id="5025"
   message="Type CopyOnWriteArrayList&lt;String&gt; satisfies the annotation bound ReferenceObject || ThreadSafe on type formal E"
   enclosed-in-folder="true"
   from-src="true"
   message-id="(496,CopyOnWriteArrayList&lt;String&gt;,ReferenceObject || ThreadSafe,E)"
   derived-from-src="true"
   consistent="true"
   proved-consistent="true"
   full-type="edu.cmu.cs.fluid.sea.ResultDrop"/>

  <result-drop type="ResultDrop"
   offset="194"
   length="31"
   line="10"
   path="TestBoundedCollections/src/test/Test.java"
   uri="file:/Users/aarong/git/regression/regression/TestBoundedCollections/src/test/Test.java"
   file="file:/Users/aarong/git/regression/regression/TestBoundedCollections/src/test/Test.java"
   hash="1461306422"
   context="-543256980"
   id="5026"
   message="Type Object does not satisfy the annotation bound ReferenceObject || ThreadSafe on type formal V"
   enclosed-in-folder="true"
   from-src="true"
   message-id="(497,Object,ReferenceObject || ThreadSafe,V)"
   derived-from-src="true"
   full-type="edu.cmu.cs.fluid.sea.ResultDrop"/>

  <result-drop type="ResultDrop"
   offset="194"
   length="31"
   line="10"
   path="TestBoundedCollections/src/test/Test.java"
   uri="file:/Users/aarong/git/regression/regression/TestBoundedCollections/src/test/Test.java"
   file="file:/Users/aarong/git/regression/regression/TestBoundedCollections/src/test/Test.java"
   hash="1461306422"
   context="-543256980"
   id="5027"
   message="Type String satisfies the annotation bound ReferenceObject || ThreadSafe on type formal K"
   enclosed-in-folder="true"
   from-src="true"
   message-id="(496,String,ReferenceObject || ThreadSafe,K)"
   derived-from-src="true"
   consistent="true"
   proved-consistent="true"
   full-type="edu.cmu.cs.fluid.sea.ResultDrop"/>

  <result-drop type="ResultDrop"
   offset="438"
   length="28"
   line="16"
   path="TestBoundedCollections/src/test/Example.java"
   uri="file:/Users/aarong/git/regression/regression/TestBoundedCollections/src/test/Example.java"
   file="file:/Users/aarong/git/regression/regression/TestBoundedCollections/src/test/Example.java"
   hash="704134106"
   context="-941332293"
   id="5028"
   message="Type String satisfies the annotation bound ReferenceObject || ThreadSafe on type formal E"
   enclosed-in-folder="true"
   from-src="true"
   message-id="(496,String,ReferenceObject || ThreadSafe,E)"
   derived-from-src="true"
   consistent="true"
   proved-consistent="true"
   full-type="edu.cmu.cs.fluid.sea.ResultDrop"/>

  <result-drop type="ResultDrop"
   offset="229"
   length="29"
   line="11"
   path="TestBoundedCollections/src/test/Test.java"
   uri="file:/Users/aarong/git/regression/regression/TestBoundedCollections/src/test/Test.java"
   file="file:/Users/aarong/git/regression/regression/TestBoundedCollections/src/test/Test.java"
   hash="787417592"
   context="-1226327922"
   id="5029"
   message="Type Integer satisfies the annotation bound ReferenceObject || ThreadSafe on type formal E"
   enclosed-in-folder="true"
   from-src="true"
   message-id="(496,Integer,ReferenceObject || ThreadSafe,E)"
   derived-from-src="true"
   consistent="true"
   proved-consistent="true"
   full-type="edu.cmu.cs.fluid.sea.ResultDrop"/>

  <result-drop type="ResultDrop"
   offset="647"
   length="68"
   line="24"
   path="TestBoundedCollections/src/test/Example.java"
   uri="file:/Users/aarong/git/regression/regression/TestBoundedCollections/src/test/Example.java"
   file="file:/Users/aarong/git/regression/regression/TestBoundedCollections/src/test/Example.java"
   hash="-956272932"
   context="1400164821"
   id="5030"
   message="Type Location satisfies the annotation bound ReferenceObject || ThreadSafe on type formal K"
   enclosed-in-folder="true"
   from-src="true"
   message-id="(496,Location,ReferenceObject || ThreadSafe,K)"
   derived-from-src="true"
   consistent="true"
   proved-consistent="true"
   full-type="edu.cmu.cs.fluid.sea.ResultDrop"/>

  <result-drop type="ResultDrop"
   offset="647"
   length="68"
   line="24"
   path="TestBoundedCollections/src/test/Example.java"
   uri="file:/Users/aarong/git/regression/regression/TestBoundedCollections/src/test/Example.java"
   file="file:/Users/aarong/git/regression/regression/TestBoundedCollections/src/test/Example.java"
   hash="-956272932"
   context="1400164821"
   id="5031"
   message="Type Player satisfies the annotation bound ReferenceObject || ThreadSafe on type formal V"
   enclosed-in-folder="true"
   from-src="true"
   message-id="(496,Player,ReferenceObject || ThreadSafe,V)"
   derived-from-src="true"
   consistent="true"
   proved-consistent="true"
   full-type="edu.cmu.cs.fluid.sea.ResultDrop"/>

  <result-drop type="ResultDrop"
   offset="261"
   length="34"
   line="12"
   path="TestBoundedCollections/src/test/Test.java"
   uri="file:/Users/aarong/git/regression/regression/TestBoundedCollections/src/test/Test.java"
   file="file:/Users/aarong/git/regression/regression/TestBoundedCollections/src/test/Test.java"
   hash="-1119661981"
   context="-1226327922"
   id="5032"
   message="Type Vector&lt;String&gt; satisfies the annotation bound ReferenceObject || ThreadSafe on type formal E"
   enclosed-in-folder="true"
   from-src="true"
   message-id="(496,Vector&lt;String&gt;,ReferenceObject || ThreadSafe,E)"
   derived-from-src="true"
   consistent="true"
   proved-consistent="true"
   full-type="edu.cmu.cs.fluid.sea.ResultDrop"/>

  <result-drop type="ResultDrop"
   offset="276"
   length="14"
   line="12"
   path="TestBoundedCollections/src/test/Test.java"
   uri="file:/Users/aarong/git/regression/regression/TestBoundedCollections/src/test/Test.java"
   file="file:/Users/aarong/git/regression/regression/TestBoundedCollections/src/test/Test.java"
   hash="-344500742"
   context="-1226327922"
   id="5033"
   message="Type String satisfies the annotation bound ReferenceObject || ThreadSafe on type formal E"
   enclosed-in-folder="true"
   from-src="true"
   message-id="(496,String,ReferenceObject || ThreadSafe,E)"
   derived-from-src="true"
   consistent="true"
   proved-consistent="true"
   full-type="edu.cmu.cs.fluid.sea.ResultDrop"/>

  <result-drop type="ResultDrop"
   offset="298"
   length="20"
   line="13"
   path="TestBoundedCollections/src/test/Test.java"
   uri="file:/Users/aarong/git/regression/regression/TestBoundedCollections/src/test/Test.java"
   file="file:/Users/aarong/git/regression/regression/TestBoundedCollections/src/test/Test.java"
   hash="-205428493"
   context="-1226327922"
   id="5034"
   message="Type Object does not satisfy the annotation bound Containable on type formal C"
   enclosed-in-folder="true"
   from-src="true"
   message-id="(497,Object,Containable,C)"
   derived-from-src="true"
   full-type="edu.cmu.cs.fluid.sea.ResultDrop"/>

</sea-summary>

